Metadata-Version: 1.1
Name: django-tastypie-swagger-python3
Version: 0.1.3
Summary: An adapter to use swagger-ui with django-tastypie
Home-page: https://github.com/williamfligor/django-tastypie-swagger
Author: Concentric Sky
Author-email: code@concentricsky.com
License: BSD
Download-URL: https://github.com/williamfligor/django-tastypie-swagger/downloads
Platform: UNKNOWN
Classifier: Programming Language :: Python
Classifier: Environment :: Web Environment
Classifier: Framework :: Django
